eoepca_uma/__init__.py
eoepca_uma/client.py
eoepca_uma/main.py
eoepca_uma/resource.py
eoepca_uma/rpt.py
eoepca_uma/utils.py
eoepca_uma/tests/__init__.py
eoepca_uma/tests/rpt_test.py
eoepca_uma-0.2.4.dist-info/LICENSE
eoepca_uma-0.2.4.dist-info/METADATA
eoepca_uma-0.2.4.dist-info/WHEEL
eoepca_uma-0.2.4.dist-info/top_level.txt
eoepca_uma-0.2.4.dist-info/RECORD
