Metadata-Version: 2.1
Name: eoepca-uma
Version: 0.2.4
Summary: Python library to interact with UMA protocol
Home-page: https://github.com/EOEPCA/um-common-uma-client 
Author: EOEPCA
Author-email: angel.lozano@deimos-space.com
License: apache-2.0
Keywords: UMA,Client,EOEPCA,user,management
Platform: UNKNOWN
Classifier: Development Status :: 3 - Alpha
Classifier: Intended Audience :: Developers
Classifier: Topic :: Software Development :: Build Tools
Requires-Python: >=3.6
License-File: LICENSE
